netgraph/__init__.py
netgraph/_arcdiagram.py
netgraph/_artists.py
netgraph/_deprecated.py
netgraph/_edge_layout.py
netgraph/_interactive_variants.py
netgraph/_line_supercover.py
netgraph/_main.py
netgraph/_node_layout.py
netgraph/_parser.py
netgraph/_utils.py
netgraph-4.13.2.dist-info/LICENSE.txt
netgraph-4.13.2.dist-info/METADATA
netgraph-4.13.2.dist-info/WHEEL
netgraph-4.13.2.dist-info/top_level.txt
netgraph-4.13.2.dist-info/RECORD
