Metadata-Version: 2.1
Name: netgraph
Version: 4.13.2
Summary: Python drawing utilities for publication quality plots of networks.
Home-page: https://github.com/paulbrodersen/netgraph
Download-URL: https://github.com/paulbrodersen/netgraph/archive/4.13.2.tar.gz
Author: Paul Brodersen
Author-email: Paul Brodersen <paulbrodersen+netgraph@gmail.com>
License: GNU General Public License v3 (GPLv3)
Project-URL: Repository, https://github.com/paulbrodersen/netgraph
Project-URL: Documentation, https://netgraph.readthedocs.io/en/latest/
Keywords: matplotlib,network,visualisation
Platform: Platform Independent
Classifier: Development Status :: 4 - Beta
Classifier: Intended Audience :: Science/Research
Classifier: License :: OSI Approved :: GNU General Public License v3 (GPLv3)
Classifier: Operating System :: OS Independent
Classifier: Programming Language :: Python :: 3
Classifier: Topic :: Scientific/Engineering :: Visualization
Requires-Python: >=3.6
License-File: LICENSE.txt
Requires-Dist: numpy
Requires-Dist: scipy
Requires-Dist: matplotlib>=1.5
Requires-Dist: rectangle-packer
Requires-Dist: grandalf
Provides-Extra: tests
Requires-Dist: pytest; extra == "tests"
Requires-Dist: pytest-mpl; extra == "tests"
Provides-Extra: docs
Requires-Dist: sphinx; extra == "docs"
Requires-Dist: sphinx-rtd-theme; extra == "docs"
Requires-Dist: numpydoc; extra == "docs"
Requires-Dist: sphinx-gallery; extra == "docs"
Requires-Dist: Pillow; extra == "docs"
Requires-Dist: networkx; extra == "docs"
